{
  "tecnologia": [
    {
      "institucion": "Universidad ORT",
      "titulo": "Analista Programador",
      "periodo": "2007",
      "habilidades": ["Visual Basic Studio", "Programación POO", "Web", "SQL", "Base de datos"],
      "certificado": "/certificados/analista.png"
    },
    {
      "institucion": "4Geeks Academy",
      "titulo": "Full Stack Software Development FT",
      "periodo": "2022",
      "habilidades": ["HTML", "CSS", "JavaScript", "React", "Python", "Formik", "Axios", "Flux", "FlaskSQLAchemy"],
      "certificado": "/certificados/full.jpg"
    },
    {
      "institucion": "Nucba",
      "titulo": "React.js",
      "periodo": "2025",
      "habilidades": ["HTML", "CSS", "JavaScript", "React", "Vite", "Formik", "Axios", "Redux Toolkit"],
      "certificado": "/certificados/reactjs.jpg"
    },
    {
      "institucion": "CoderHouse",
      "titulo": "Angular",
      "periodo": "2025",
      "habilidades": ["HTML", "CSS", "TypeScript", "Angular", "Bootstrap"],
      "certificado": "/certificados/angular.jpg"
    },
    {
      "institucion": "CoderHouse",
      "titulo": "WordPress",
      "periodo": "2025",
      "habilidades": ["WordPress", "CSS", "Elementor", "Widgets"],
      "certificado": "/certificados/wordpress.jpg"
    },
    {
      "institucion": "Nucba",
      "titulo": "JavaScript",
      "periodo": "2025",
      "habilidades": ["HTML", "CSS", "JavaScript"],
      "certificado": "/certificados/js.jpg"
    },
    {
      "institucion": "CoderHouse",
      "titulo": "Python Django",
      "periodo": "2025",
      "habilidades": ["HTML", "CSS", "Bootstrap", "Pyhton", "Django"],
      "certificado": "/certificados/django.jpg"
    },
    {
      "institucion": "Nucba",
      "titulo": "Diseño web",
      "periodo": "2024",
      "habilidades": ["HTML", "CSS"],
      "certificado": "/certificados/js.jpg"
    },
    {
      "institucion": "CoderHouse",
      "titulo": "Cloud Computing",
      "periodo": "2024",
      "habilidades": ["AWS", "Cloud Computing"],
      "certificado": "/certificados/aws.jpg"
    },
    {
      "institucion": "CoderHouse",
      "titulo": "Desarrollo de aplicaciones",
      "periodo": "2024",
      "habilidades": ["HTML", "CSS", "React Native", "Redux", "Firebase", "Google Auth"],
      "certificado": "/certificados/native.jpg"
    },
    {
      "institucion": "CoderHouse",
      "titulo": "Next.js",
      "periodo": "2024",
      "habilidades": ["HTML", "CSS", "TailwindCSS", "Next.js", "Firebase", "Google Auth", "Redux"],
      "certificado": "/certificados/next.jpg"
    },
    {
      "institucion": "Plataforma 5",
      "titulo": "Curso introductorio de Programación",
      "periodo": "2022",
      "habilidades": ["HTML", "CSS", "JavaScript"],
      "certificado": "/certificados/introjs.jpg"
    },
    {
      "institucion": "CoderHouse",
      "titulo": "Programación Backend",
      "periodo": "2022",
      "habilidades": ["HTML", "CSS", "JavaScript", "Node.js", "Docker"],
      "certificado": "/certificados/backend.jpg"
    },
    {
      "institucion": "Taller de informática",
      "titulo": "Programación JavaScript",
      "periodo": "2021",
      "habilidades": ["HTML", "CSS", "JavaScript"],
      "certificado": "/certificados/jstaller.jpg"
    }
  ],
  "marketing": [
    {
      "institucion": "CoderHouse",
      "titulo": "Publicidad en Redes Avanzado",
      "periodo": "2025",
      "habilidades": ["Meta Ads", "Google Ads"],
      "certificado": "/certificados/publicidadredes.jpg"
    },
    {
      "institucion": "Skillshop de Google",
      "titulo": "Publicidad en Display de Google Ads",
      "periodo": "2025",
      "habilidades": ["Meta Ads", "Google Ads"],
      "certificado": "/certificados/display.jpg"
    },
    {
      "institucion": "Skillshop de Google",
      "titulo": "Publicidad en Búsqueda de Google Ads",
      "periodo": "2025",
      "habilidades": ["Meta Ads", "Google Ads"],
      "certificado": "/certificados/busqueda.jpg"
    },
    {
      "institucion": "CoderHouse",
      "titulo": "Marketing Digital",
      "periodo": "2025",
      "habilidades": ["Meta Ads", "Google Ads"],
      "certificado": "/certificados/marketing.jpg"
    },
    {
      "institucion": "Santander Open Academy",
      "titulo": "StoryTelling en el marketing digital",
      "periodo": "2024",
      "habilidades": ["StoryTelling"],
      "certificado": "/certificados/story.jpg"
    }
  ],
  "metodologias": [
    {
      "institucion": "Santander Open Academy",
      "titulo": "Liderazgo",
      "periodo": "2024",
      "habilidades": ["Liderazgo", "Trabajo en equipo"],
      "certificado": "/certificados/liderazgosant.jpg"
    },
    {
      "institucion": "Bios Online",
      "titulo": "Scrum, Jira y Metodologías ágiles",
      "periodo": "2023",
      "habilidades": ["Scrum", "Trabajo en equipo", "Metodologías ágiles", "Jira"],
      "certificado": "/certificados/jira.png"
    },
    {
      "institucion": "Scrum Foundation",
      "titulo": "Scrum Fundamentals",
      "periodo": "2023",
      "habilidades": ["Scrum", "Trabajo en equipo", "Metodologías ágiles"],
      "certificado": "/certificados/scrum.jpg"
    },
    {
      "institucion": "Bios Online",
      "titulo": "Liderazgo para principiantes",
      "periodo": "2023",
      "habilidades": ["Liderazgo", "Trabajo en equipo"],
      "certificado": "/certificados/liderazgo.png"
    }
  ],
  "ux": [
    {
      "institucion": "Open Bootcamp",
      "titulo": "UX/UI",
      "periodo": "2023",
      "habilidades": ["UX", "UI", "Figma"],
      "certificado": "/certificados/uxui.jpg"
    },
    {
      "institucion": "Domestika",
      "titulo": "Diseño de interfaces web y aplicaciones",
      "periodo": "2021",
      "habilidades": ["UX", "UI", "Figma"],
      "certificado": "/certificados/interfaces.png"
    }
  ]
}

